MANIFEST.in
__init__.py
compare_img.py
constants.py
get_start_time.py
image_matcher.py
match_conf.py
matching.py
read_frame.py
test.py
tmp_image_utils.py
appinit_test.egg-info/PKG-INFO
appinit_test.egg-info/SOURCES.txt
appinit_test.egg-info/dependency_links.txt
appinit_test.egg-info/requires.txt
appinit_test.egg-info/top_level.txt
conf/__init__.py
conf/config.yaml
initapp_test.egg-info/PKG-INFO
initapp_test.egg-info/SOURCES.txt
initapp_test.egg-info/dependency_links.txt
initapp_test.egg-info/requires.txt
initapp_test.egg-info/top_level.txt
initcost_conf/__init__.py
initcost_conf/config.yaml
match_cost/__init__.py
match_cost/compare_img.py
match_cost/get_start_time.py
match_cost/image_matcher.py
match_cost/match_conf.py
match_cost/matching.py
match_cost/pytesseract.py
match_cost/read_frame.py
match_cost/tmp_image_utils.py
tmp_img/__init__.py
tmp_img/match_config.yaml
tmp_img/android/vedio_load_tmp_1.jpg
tmp_img/android/vedio_load_tmp_2.jpg
tmp_img/android/TT/TT_splash.png
tmp_img/android/TT/TT_tab.png
tmp_img/android/TT/feed/like.png
tmp_img/android/TT/feed/like1.png
tmp_img/android/TT/splash/TT_splash.png
tmp_img/android/TT/tab/TT_tab.png
tmp_img/android/TT/tab/TT_tab1.png
tmp_img/android/TT/tab/1440_3040/TT_tab1.png
tmp_img/android/TT/tab/1440_3040/tab.png
tmp_img/android/TT/tab/540_960/tab.png
tmp_img/android/TT/tab/720_1280/TT_tab1.png
tmp_img/android/TT/tab/720_1560/TT_tab1.png
tmp_img/android/kwai/kwaipro.png
tmp_img/android/kwai/splash_tmp.png
tmp_img/android/kwai/vedio_load_tmp.jpg
tmp_img/android/kwai/576_1248/vedio_load_tmp.jpg
tmp_img/android/kwai/600_12801/vedio_load_tmp.jpg
tmp_img/android/kwai/feed/arrow.png
tmp_img/android/kwai/feed/comment.png
tmp_img/android/kwai/feed/like.png
tmp_img/android/kwai/feed/like0.png
tmp_img/android/kwai/feed/like1.png
tmp_img/android/kwai/feed/like2.png
tmp_img/android/kwai/splash/splash_tmp.png
tmp_img/android/kwai/tab/kwaipro.png
tmp_img/android/kwai/tab/1440_3040/tab.png
tmp_img/android/kwai/tab/540_960/tab.png
tmp_img/android/kwai/tab/720_1560/kwai_tab.png
tmp_img/android/kwai/vediotmp/vedio_load_tmp.jpg
tmp_img/android/kwai/vediotmp/1080_2340/vedio_load_tmp.jpg
tmp_img/android/kwai/vediotmp/1080_2340/vedio_load_tmp_auto_1657077932.jpg
tmp_img/android/kwai/vediotmp/1440_3040/vedio_load_tmp.jpg
tmp_img/android/kwai/vediotmp/368_800/vedio_load_tmp.jpg
initapp_test-4.0.13.dist-info/METADATA
initapp_test-4.0.13.dist-info/WHEEL
initapp_test-4.0.13.dist-info/top_level.txt
initapp_test-4.0.13.dist-info/RECORD
